{
    "alert.login_success"       : "Logged in successfully.",
    "alert.login_error"         : "Verify your credentials.",
    "alert.logout_success"      : "Logged out successfully.",

    "btn.login"                 : "Log In",

    "label.email"               : "Email",
    "label.password"            : "Password",
    "label.remember"            : "Remember me",

    "menu.analytics"            : "Analytics",
    "menu.logout"               : "Logout",
    "menu.users"                : "Users",

    "placeholder.email"         : "Email",
    "placeholder.password"      : "Password",

    "title.login"               : "Log in"
}